[
  {
    "Name": "BCR",
    "Swift": "dsf232e",
    "Accounts": []
  },
  {
    "Name": "Revolut",
    "Swift": "REVOROBU",
    "Accounts": [
      {
        "AccountHolder": "Pop Patric",
        "AccountType": 0,
        "AccountCurrency": 3,
        "Iban": "RO38REVO1666586259441570",
        "Amount": 10939500.00,
        "Transactions": [
          {
            "Date": "2025-10-18T14:28:05.6669441Z",
            "Description": "Deposit",
            "Amount": 13000000
          },
          {
            "Date": "2025-10-18T14:28:24.7790064Z",
            "Description": "Currency change to GBP (fee 130000.00)",
            "Amount": 10939500.00
          }
        ],
        "AccountFeeCurrencyChange": 0.01
      }
    ]
  },
  {
    "Name": "Unicredit",
    "Swift": "UNICROBU",
    "Accounts": [
      {
        "AccountHolder": "Manea Ioana Raluca",
        "AccountType": 0,
        "AccountCurrency": 3,
        "Iban": "RO86UNIC3110723461536466",
        "Amount": 84149999999999999999.16,
        "Transactions": [
          {
            "Date": "2025-10-18T15:34:17.7602888Z",
            "Description": "Deposit",
            "Amount": 99999999999999999999
          },
          {
            "Date": "2025-10-18T15:34:37.666393Z",
            "Description": "Currency change to GBP (fee 999999999999999999.99)",
            "Amount": 84149999999999999999.16
          }
        ],
        "AccountFeeCurrencyChange": 0.01
      }
    ]
  }
]